Metadata-Version: 2.1
Name: onnxcustom
Version: 0.4.293
Summary: Extends scikit-learn with a couple of new models, transformers, metrics, plotting.
Home-page: http://www.xavierdupre.fr/app/onnxcustom/helpsphinx/index.html
Author: Xavier Dupré
Author-email: xavier.dupre@gmail.com
License: MIT
Download-URL: https://github.com/sdpython/onnxcustom/
Keywords: onnxcustom,Xavier Dupré
Platform: UNKNOWN
Classifier: Programming Language :: Python :: 3
Classifier: Intended Audience :: Developers
Classifier: Topic :: Scientific/Engineering
Classifier: Topic :: Education
Classifier: License :: OSI Approved :: MIT License
Classifier: Development Status :: 5 - Production/Stable
Requires-Dist: fire
Requires-Dist: numpy
Requires-Dist: onnx (>=1.10.1)
Requires-Dist: scipy
Provides-Extra: all
Requires-Dist: fire ; extra == 'all'
Requires-Dist: numpy ; extra == 'all'
Requires-Dist: onnx (>=1.10.1) ; extra == 'all'
Requires-Dist: scipy ; extra == 'all'
Requires-Dist: pandas-streaming (>=0.3) ; extra == 'all'
Requires-Dist: cxxfilt ; extra == 'all'
